macwinnie_pyhelpers/Browser.py
macwinnie_pyhelpers/CSV.py
macwinnie_pyhelpers/Metrics.py
macwinnie_pyhelpers/PyHistory.py
macwinnie_pyhelpers/SententialLogic.py
macwinnie_pyhelpers/Version.py
macwinnie_pyhelpers/__init__.py
macwinnie_pyhelpers/tpl/metrics.j2
macwinnie_pyhelpers-3.0.4.dist-info/LICENSE
macwinnie_pyhelpers-3.0.4.dist-info/METADATA
macwinnie_pyhelpers-3.0.4.dist-info/WHEEL
macwinnie_pyhelpers-3.0.4.dist-info/RECORD
