Metadata-Version: 2.3
Name: macwinnie-pyhelpers
Version: 3.0.4
Summary: Set of python helpers for daily jobs
License: GNU AFFERO GENERAL PUBLIC LICENSE
Author: macwinnie
Author-email: dev@macwinnie.me
Requires-Python: >=3.11,<4
Classifier: License :: OSI Approved :: GNU Affero General Public License v3 or later (AGPLv3+)
Classifier: License :: Other/Proprietary License
Classifier: Operating System :: OS Independent
Classifier: Programming Language :: Python :: 3
Classifier: Programming Language :: Python :: 3.11
Classifier: Programming Language :: Python :: 3.12
Classifier: Programming Language :: Python :: 3.13
Provides-Extra: all
Provides-Extra: browser
Provides-Extra: csv
Requires-Dist: jinja2 (>=3.1.2,<4.0.0)
Requires-Dist: pandas (>=2.1.2,<3.0.0) ; extra == "all" or extra == "csv"
Requires-Dist: selenium (>=4.16.0,<5.0.0) ; extra == "all" or extra == "browser"
Project-URL: Homepage, https://macwinnie.github.io/python-helpers
Project-URL: Repository, https://github.com/macwinnie/python-helpers/
